CHANGES.txt
README.txt
setup.py
src/ks/__init__.py
src/ks.reference.egg-info/PKG-INFO
src/ks.reference.egg-info/SOURCES.txt
src/ks.reference.egg-info/dependency_links.txt
src/ks.reference.egg-info/namespace_packages.txt
src/ks.reference.egg-info/not-zip-safe
src/ks.reference.egg-info/requires.txt
src/ks.reference.egg-info/top_level.txt
src/ks/reference/INSTALL.txt
src/ks/reference/LICENSE.txt
src/ks/reference/README.txt
src/ks/reference/__init__.py
src/ks/reference/configure.zcml
src/ks/reference/reference.txt
src/ks/reference/reference_doc.txt
src/ks/reference/browser/__init__.py
src/ks/reference/browser/configure.zcml
src/ks/reference/browser/referenceedit.pt
src/ks/reference/browser/referenceedit.py
src/ks/reference/browser/referenceedit.txt
src/ks/reference/browser/selectreftype.pt
src/ks/reference/demo/__init__.py
src/ks/reference/demo/configure.zcml
src/ks/reference/demo/etc/referencedemo-configure.zcml
src/ks/reference/etc/ks.reference-configure.zcml
src/ks/reference/etc/ks.reference.referencezcml-meta.zcml
src/ks/reference/reference/__init__.py
src/ks/reference/reference/configure.zcml
src/ks/reference/reference/interfaces.py
src/ks/reference/reference/referencebase.py
src/ks/reference/reference/referencebase.txt
src/ks/reference/referenceannotation/__init__.py
src/ks/reference/referenceannotation/configure.zcml
src/ks/reference/referenceannotation/interfaces.py
src/ks/reference/referenceannotation/referenceannotableadapter.py
src/ks/reference/referenceannotation/referenceannotation.py
src/ks/reference/referenceannotation/referenceannotation.txt
src/ks/reference/referencehandlers/__init__.py
src/ks/reference/referencehandlers/configure.zcml
src/ks/reference/referencehandlers/referencehandlers.py
src/ks/reference/referencezcml/__init__.py
src/ks/reference/referencezcml/meta.zcml
src/ks/reference/referencezcml/metaconfigure.py
src/ks/reference/referencezcml/metadirectives.py
src/ks/reference/referencezcml/referencezcml.txt
