Metadata-Version: 1.0
Name: ks.reference
Version: 1.0.1
Summary: Referene package for zope3
Home-page: http://code.keysolutions.ru/svn/ks.reference
Author: Key Solutions Development TEAM
Author-email: ksd-team@keysolutions.ru
License: ZPL v2.1
Platform: UNKNOWN
Classifier: Environment :: Web Environment
Classifier: Intended Audience :: Developers
Classifier: License :: OSI Approved :: Zope Public License
Classifier: Programming Language :: Python
Classifier: Operating System :: OS Independent
Classifier: Topic :: Internet :: WWW/HTTP
Classifier: Framework :: Zope3
